{
  "matrix_name": "adam-tiny-clean-profile-experiment-matrix",
  "suite_name": "adam-tiny-clean-profile-suite",
  "strategy_name": "adam-tiny-clean-profile-strategy",
  "promotion_name": "unselected",
  "expected_active_profile": "reference_heavy",
  "active_profile": "reference_heavy",
  "candidate_count": 5,
  "best_profile": "reference_heavy",
  "best_validation_exact_match_rate_bps": 10000,
  "matrix_checks": [
    {
      "check": "expected_active_profile_included",
      "passed": true
    },
    {
      "check": "reference_profile_is_promotable",
      "passed": true
    },
    {
      "check": "candidate_profiles_are_promotable",
      "passed": true
    },
    {
      "check": "candidate_count_matches_manifest",
      "passed": true
    }
  ],
  "entry_reports": [
    {
      "profile": "balanced",
      "pack_name": "adam-tiny-clean-balanced-pack",
      "is_active_profile": false,
      "is_promotable_profile": false,
      "sample_count": 27,
      "train_token_count": 158,
      "vocabulary_size": 79,
      "deterministic_context_count": 61,
      "ambiguous_context_count": 21,
      "validation_exact_match_rate_bps": 3333,
      "validation_gap_bps": 6667
    },
    {
      "profile": "education_heavy",
      "pack_name": "adam-tiny-clean-education-heavy-pack",
      "is_active_profile": false,
      "is_promotable_profile": false,
      "sample_count": 24,
      "train_token_count": 140,
      "vocabulary_size": 76,
      "deterministic_context_count": 58,
      "ambiguous_context_count": 21,
      "validation_exact_match_rate_bps": 4615,
      "validation_gap_bps": 5385
    },
    {
      "profile": "education_max",
      "pack_name": "adam-tiny-clean-education-max-pack",
      "is_active_profile": false,
      "is_promotable_profile": false,
      "sample_count": 24,
      "train_token_count": 139,
      "vocabulary_size": 78,
      "deterministic_context_count": 59,
      "ambiguous_context_count": 22,
      "validation_exact_match_rate_bps": 4000,
      "validation_gap_bps": 6000
    },
    {
      "profile": "general_heavy",
      "pack_name": "adam-tiny-clean-general-heavy-pack",
      "is_active_profile": false,
      "is_promotable_profile": false,
      "sample_count": 24,
      "train_token_count": 140,
      "vocabulary_size": 68,
      "deterministic_context_count": 53,
      "ambiguous_context_count": 18,
      "validation_exact_match_rate_bps": 5714,
      "validation_gap_bps": 4286
    },
    {
      "profile": "reference_heavy",
      "pack_name": "adam-tiny-clean-reference-heavy-pack",
      "is_active_profile": true,
      "is_promotable_profile": true,
      "sample_count": 24,
      "train_token_count": 140,
      "vocabulary_size": 71,
      "deterministic_context_count": 53,
      "ambiguous_context_count": 21,
      "validation_exact_match_rate_bps": 10000,
      "validation_gap_bps": 0
    }
  ]
}
